CHANGELOG.md
MANIFEST.in
README.md
STYLE.md
setup.py
phantom/__init__.py
phantom/align.py
phantom/clustering.py
phantom/enhance.py
phantom/geometry.py
phantom/similarity.py
phantom/utils.py
phantom/video.py
phantom.egg-info/PKG-INFO
phantom.egg-info/SOURCES.txt
phantom.egg-info/dependency_links.txt
phantom.egg-info/requires.txt
phantom.egg-info/top_level.txt
phantom/faces/__init__.py
phantom/faces/align.py
phantom/faces/faces.py
phantom/measures/__init__.py
phantom/measures/calibrate.py
phantom/measures/measure.py
phantom/models/dlib_face_recognition_resnet_model_v1.dat
phantom/models/mmod_human_face_detector.dat
phantom/models/phantom_age_model_v1.dat
phantom/models/phantom_gender_model_v1.dat
phantom/models/phantom_gender_model_v1_dlib_19.8.dat
phantom/models/phantom_gender_model_v1b.dat
phantom/models/phantom_gender_model_v1c.dat
phantom/models/shape_predictor_5_face_landmarks.dat