Metadata-Version: 1.2
Name: phantom
Version: 0.7.2
Summary: a library for working with faces in python
Home-page: https://github.com/bconstanzo/phantom
Author: Bruno Constanzo
Author-email: bconstanzo@ufasta.edu.ar
License: LGPL 2.1
Platform: UNKNOWN
Requires-Python: >=3.6
